{
    "standard_diseases": [
        "BỆNH DA VÀ NIÊM MẠC DO CANDIDA (Candidosis)",
        "BỆNH LAO DA",
        "BỆNH LẬU (Gonorrhea)",
        "VIÊM BÌ CƠ (Dermatomyositis)",
        "BỆNH GIANG MAI (Syphilis)",
        "BỆNH PORPHYRIN DA",
        "LY THƯỢNG BÌ BỌNG NƯỚC BẨM SINH (Inherited epidermolysis bullosa)",
        "PEMPHIGUS",
        "BỆNH LICHEN PHẲNG (Lichen planus)",
        "HỒNG BAN ĐA DẠNG (Erythema multiforme)",
        "VIÊM NANG LÔNG (Folliculitis)",
        "VIÊM ÂM HỘ-ÂM ĐẠO DO NẤM CANDIDA (Vulvovaginal Candidiasis)",
        "BỆNH GAI ĐEN (Acanthosis nigricans)",
        "BỆNH PELLAGRA",
        "SẠM DA",
        "DÀY SỪNG LÒNG BÀN TAY, BÀN CHÂN DI TRUYỀN",
        "NẤM MÓNG (Onychomycosis)",
        "UNG THƯ TẾ BÀO VẢY (Squamous cell carcinoma-SCC)",
        "VIÊM DA TIẾP XÚC DỊ ỨNG (Allergic Contact Dermatitis)",
        "BỆNH LUPUS BAN ĐỎ (Lupus Erythematosus)",
        "BỆNH MÀY ĐAY (Urticaria)",
        "BỆNH VIÊM DA DẠNG HERPES CỦA DUHRING-BROCQ (Dermatitis Herpetiformis)",
        "LANG BEN",
        "BỆNH GHẺ (Scabies)",
        "HỘI CHỨNG STEVENS-JOHNSON (Stevens-Johnson syndrome - SJS)",
        "NHỌT",
        "RÁM MÁ (Chloasma)",
        "U ỐNG TUYẾN MỒ HÔI (Syringoma)",
        "BỆNH VẢY NẾN (Psoriasis)",
        "HỘI CHỨNG DRESS (The Drug Reaction with Eosinophilia and Systemic Symptoms)",
        "UNG THƯ TẾ BÀO HẮC TỐ (Malignant melanoma)",
        "Á VẢY NẾN VÀ VẢY PHẤN DẠNG LICHEN (Parapsoriasis and Pityriasis Lichenoides)",
        "BỆNH SÙI MÀO GÀ SINH DỤC (Genital wart)",
        "HERPES SINH DỤC (Genital herpes simplex viral infections)",
        "UNG THƯ TẾ BÀO ĐÁY (Basal cell carcinoma - BCC)",
        "ĐỎ DA TOÀN THÂN (Erythroderma)",
        "HỘI CHỨNG RAYNAUD",
        "SẨN NGỨA (Prurigo)",
        "VIÊM ÂM ĐẠO DO TRÙNG ROI (Trichomoniasis)",
        "VẢY PHẤN HỒNG GIBERT (Pityriasis rosea of Gibert)",
        "DỊ SỪNG NANG LÔNG (Follicular dyskeratosis)",
        "HỘI CHỨNG LYELL",
        "NHIỄM CHLAMYDIA TRACHOMATIS SINH DỤC-TIẾT NIỆU (Chlamydia trachomatis infections)",
        "VIÊM DA ĐẦU CHI - RUỘT (Acrodermatitis enteropathica)",
        "BỆNH DA DO ÁNH SÁNG (Photodermatosis)",
        "BỆNH DA NGHỀ NGHIỆP (Occupational skin diseases)",
        "U MỀM LÂY (Molluscum Contagiosum)",
        "U XƠ THẦN KINH (Neurofibromatosis)",
        "VIÊM DA DẦU (Seborrheic Dermatitis)",
        "BỆNH BẠCH BIẾN (Vitiligo)",
        "BỆNH PHONG (Leprosy)",
        "HỘI CHỨNG BONG VẢY DA DO TỤ CẦU (STAPHYLOCOCCAL SCALDED SKIN SYNDROME - SSSS)",
        "TRỨNG CÁ (Acne)",
        "BỆNH CHỐC (Impetigo)",
        "BỆNH DA DO NẤM SỢI",
        "BỆNH VẢY CÁ MẮC PHẢI",
        "BỆNH ZONA",
        "NẤM TÓC",
        "SARCOIDOSIS",
        "BỆNH HẠT CƠM (Warts)",
        "BỆNH VẢY PHẤN ĐỎ NANG LÔNG (Pityriasis rubra pilaris)",
        "VIÊM DA CƠ ĐỊA (Atopic dermatitis)",
        "VIÊM DA TIẾP XÚC DO CÔN TRÙNG",
        "BỆNH APTHOSE (Apthosis)",
        "BỌNG NƯỚC DẠNG PEMPHIGUS (Pemphigoid)"
    ],
    "actual_disease_entities": {
        "BỆNH DA VÀ NIÊM MẠC DO CANDIDA (Candidosis)": "bệnh da và niêm mạc do candida",
        "BỆNH LAO DA": "bệnh lao da",
        "BỆNH LẬU (Gonorrhea)": "bệnh lậu",
        "VIÊM BÌ CƠ (Dermatomyositis)": "viêm bì cơ",
        "BỆNH GIANG MAI (Syphilis)": "bệnh giang mai",
        "BỆNH PORPHYRIN DA": "bệnh porphyrin da",
        "LY THƯỢNG BÌ BỌNG NƯỚC BẨM SINH (Inherited epidermolysis bullosa)": "ly thượng bì bọng nước bẩm sinh",
        "PEMPHIGUS": "pemphigus",
        "BỆNH LICHEN PHẲNG (Lichen planus)": "bệnh lichen phẳng",
        "HỒNG BAN ĐA DẠNG (Erythema multiforme)": "hồng ban đa dạng",
        "VIÊM NANG LÔNG (Folliculitis)": "viêm nang lông",
        "VIÊM ÂM HỘ-ÂM ĐẠO DO NẤM CANDIDA (Vulvovaginal Candidiasis)": "viêm âm hộ-âm đạo do nấm candida",
        "BỆNH GAI ĐEN (Acanthosis nigricans)": "bệnh gai đen",
        "BỆNH PELLAGRA": "bệnh pellagra",
        "SẠM DA": "sạm da",
        "DÀY SỪNG LÒNG BÀN TAY, BÀN CHÂN DI TRUYỀN": "dày sừng lòng bàn tay, bàn chân di truyền",
        "NẤM MÓNG (Onychomycosis)": "nấm móng",
        "UNG THƯ TẾ BÀO VẢY (Squamous cell carcinoma-SCC)": "ung thư tế bào vảy",
        "VIÊM DA TIẾP XÚC DỊ ỨNG (Allergic Contact Dermatitis)": "viêm da tiếp xúc dị ứng",
        "BỆNH LUPUS BAN ĐỎ (Lupus Erythematosus)": "lupus ban đỏ",
        "BỆNH MÀY ĐAY (Urticaria)": "bệnh mày đay",
        "BỆNH VIÊM DA DẠNG HERPES CỦA DUHRING-BROCQ (Dermatitis Herpetiformis)": "bệnh viêm da dạng herpes của duhring-brocq",
        "LANG BEN": "lang ben",
        "BỆNH GHẺ (Scabies)": "bệnh ghẻ",
        "HỘI CHỨNG STEVENS-JOHNSON (Stevens-Johnson syndrome - SJS)": "hội chứng stevens-johnson",
        "NHỌT": "nhọt",
        "RÁM MÁ (Chloasma)": "rám má",
        "U ỐNG TUYẾN MỒ HÔI (Syringoma)": "u ống tuyến mồ hôi",
        "BỆNH VẢY NẾN (Psoriasis)": "bệnh vảy nến",
        "HỘI CHỨNG DRESS (The Drug Reaction with Eosinophilia and Systemic Symptoms)": "hội chứng dress",
        "UNG THƯ TẾ BÀO HẮC TỐ (Malignant melanoma)": "ung thư tế bào hắc tố",
        "Á VẢY NẾN VÀ VẢY PHẤN DẠNG LICHEN (Parapsoriasis and Pityriasis Lichenoides)": "vảy phấn dạng lichen",
        "BỆNH SÙI MÀO GÀ SINH DỤC (Genital wart)": "bệnh sùi mào gà sinh dục",
        "HERPES SINH DỤC (Genital herpes simplex viral infections)": "herpes sinh dục",
        "UNG THƯ TẾ BÀO ĐÁY (Basal cell carcinoma - BCC)": "ung thư tế bào đáy",
        "ĐỎ DA TOÀN THÂN (Erythroderma)": "đỏ da toàn thân",
        "HỘI CHỨNG RAYNAUD": "hội chứng raynaud",
        "SẨN NGỨA (Prurigo)": "sẩn ngứa",
        "VIÊM ÂM ĐẠO DO TRÙNG ROI (Trichomoniasis)": "viêm âm đạo do trùng roi",
        "VẢY PHẤN HỒNG GIBERT (Pityriasis rosea of Gibert)": "vảy phấn hồng gibert",
        "DỊ SỪNG NANG LÔNG (Follicular dyskeratosis)": "dị sừng nang lông",
        "HỘI CHỨNG LYELL": "hội chứng lyell",
        "NHIỄM CHLAMYDIA TRACHOMATIS SINH DỤC-TIẾT NIỆU (Chlamydia trachomatis infections)": "nhiễm chlamydia trachomatis sinh dục-tiết niệu",
        "VIÊM DA ĐẦU CHI - RUỘT (Acrodermatitis enteropathica)": "viêm da đầu chi - ruột",
        "BỆNH DA DO ÁNH SÁNG (Photodermatosis)": "bệnh da do ánh sáng",
        "BỆNH DA NGHỀ NGHIỆP (Occupational skin diseases)": "bệnh da nghề nghiệp",
        "U MỀM LÂY (Molluscum Contagiosum)": "u mềm lây",
        "U XƠ THẦN KINH (Neurofibromatosis)": "u xơ thần kinh",
        "VIÊM DA DẦU (Seborrheic Dermatitis)": "viêm da dầu",
        "BỆNH BẠCH BIẾN (Vitiligo)": "bệnh bạch biến",
        "BỆNH PHONG (Leprosy)": "bệnh phong",
        "HỘI CHỨNG BONG VẢY DA DO TỤ CẦU (STAPHYLOCOCCAL SCALDED SKIN SYNDROME - SSSS)": "hội chứng bong vảy da do tụ cầu",
        "TRỨNG CÁ (Acne)": "trứng cá",
        "BỆNH CHỐC (Impetigo)": "bệnh chốc",
        "BỆNH DA DO NẤM SỢI": "bệnh da do nấm sợi",
        "BỆNH VẢY CÁ MẮC PHẢI": "bệnh vảy cá mắc phải",
        "BỆNH ZONA": "bệnh zona",
        "NẤM TÓC": "nấm tóc",
        "SARCOIDOSIS": "sarcoidosis",
        "BỆNH HẠT CƠM (Warts)": "bệnh hạt cơm",
        "BỆNH VẢY PHẤN ĐỎ NANG LÔNG (Pityriasis rubra pilaris)": "bệnh vảy phấn đỏ nang lông",
        "VIÊM DA CƠ ĐỊA (Atopic dermatitis)": "viêm da cơ địa",
        "VIÊM DA TIẾP XÚC DO CÔN TRÙNG": "viêm da tiếp xúc do côn trùng",
        "BỆNH APTHOSE (Apthosis)": "bệnh apthose",
        "BỌNG NƯỚC DẠNG PEMPHIGUS (Pemphigoid)": "bọng nước dạng pemphigus"
    },
    "disease_entities": [
        "bệnh da và niêm mạc do candida",
        "bệnh lao da",
        "bệnh lậu",
        "viêm bì cơ",
        "bệnh giang mai",
        "bệnh porphyrin da",
        "ly thượng bì bọng nước bẩm sinh",
        "pemphigus",
        "bệnh lichen phẳng",
        "hồng ban đa dạng",
        "viêm nang lông",
        "viêm âm hộ-âm đạo do nấm candida",
        "bệnh gai đen",
        "bệnh pellagra",
        "sạm da",
        "dày sừng lòng bàn tay, bàn chân di truyền",
        "nấm móng",
        "ung thư tế bào vảy",
        "viêm da tiếp xúc dị ứng",
        "lupus ban đỏ",
        "bệnh mày đay",
        "bệnh viêm da dạng herpes của duhring-brocq",
        "lang ben",
        "bệnh ghẻ",
        "hội chứng stevens-johnson",
        "nhọt",
        "rám má",
        "u ống tuyến mồ hôi",
        "bệnh vảy nến",
        "hội chứng dress",
        "ung thư tế bào hắc tố",
        "vảy phấn dạng lichen",
        "bệnh sùi mào gà sinh dục",
        "herpes sinh dục",
        "ung thư tế bào đáy",
        "đỏ da toàn thân",
        "hội chứng raynaud",
        "sẩn ngứa",
        "viêm âm đạo do trùng roi",
        "vảy phấn hồng gibert",
        "dị sừng nang lông",
        "hội chứng lyell",
        "nhiễm chlamydia trachomatis sinh dục-tiết niệu",
        "viêm da đầu chi - ruột",
        "bệnh da do ánh sáng",
        "bệnh da nghề nghiệp",
        "u mềm lây",
        "u xơ thần kinh",
        "viêm da dầu",
        "bệnh bạch biến",
        "bệnh phong",
        "hội chứng bong vảy da do tụ cầu",
        "trứng cá",
        "bệnh chốc",
        "bệnh da do nấm sợi",
        "bệnh vảy cá mắc phải",
        "bệnh zona",
        "nấm tóc",
        "sarcoidosis",
        "bệnh hạt cơm",
        "bệnh vảy phấn đỏ nang lông",
        "viêm da cơ địa",
        "viêm da tiếp xúc do côn trùng",
        "bệnh apthose",
        "bọng nước dạng pemphigus"
    ],
    "disease_document_path": {
        "BỆNH DA NGHỀ NGHIỆP (Occupational skin diseases)": "chunked_data/BỆNH_DA_NGHỀ_NGHIỆP_(Occupational_skin_diseases)",
        "BỆNH CHỐC (Impetigo)": "chunked_data/BỆNH_CHỐC_(Impetigo)",
        "VIÊM DA CƠ ĐỊA (Atopic dermatitis)": "chunked_data/VIÊM_DA_CƠ_ĐỊA_(Atopic_dermatitis)",
        "UNG THƯ TẾ BÀO ĐÁY (Basal cell carcinoma - BCC)": "chunked_data/UNG_THƯ_TẾ_BÀO_ĐÁY_(Basal_cell_carcinoma_-_BCC)",
        "VIÊM BÌ CƠ (Dermatomyositis)": "chunked_data/VIÊM_BÌ_CƠ_(Dermatomyositis)",
        "HỘI CHỨNG LYELL": "chunked_data/HỘI_CHỨNG_LYELL",
        "UNG THƯ TẾ BÀO HẮC TỐ (Malignant melanoma)": "chunked_data/UNG_THƯ_TẾ_BÀO_HẮC_TỐ_(Malignant_melanoma)",
        "NẤM MÓNG (Onychomycosis)": "chunked_data/NẤM_MÓNG_(Onychomycosis)",
        "HỘI CHỨNG RAYNAUD": "chunked_data/HỘI_CHỨNG_RAYNAUD",
        "BỆNH GHẺ (Scabies)": "chunked_data/BỆNH_GHẺ_(Scabies)",
        "HERPES SINH DỤC (Genital herpes simplex viral infections)": "chunked_data/HERPES_SINH_DỤC_(Genital_herpes_simplex_viral_infections)",
        "VIÊM ÂM ĐẠO DO TRÙNG ROI (Trichomoniasis)": "chunked_data/VIÊM_ÂM_ĐẠO_DO_TRÙNG_ROI_(Trichomoniasis)",
        "BỆNH SÙI MÀO GÀ SINH DỤC (Genital wart)": "chunked_data/BỆNH_SÙI_MÀO_GÀ_SINH_DỤC_(Genital_wart)",
        "U MỀM LÂY (Molluscum Contagiosum)": "chunked_data/U_MỀM_LÂY_(Molluscum_Contagiosum)",
        "BỆNH DA DO NẤM SỢI": "chunked_data/BỆNH_DA_DO_NẤM_SỢI",
        "RÁM MÁ (Chloasma)": "chunked_data/RÁM_MÁ_(Chloasma)",
        "NHIỄM CHLAMYDIA TRACHOMATIS SINH DỤC-TIẾT NIỆU (Chlamydia trachomatis infections)": "chunked_data/NHIỄM_CHLAMYDIA_TRACHOMATIS_SINH_DỤC-TIẾT_NIỆU_(Chlamydia_trachomatis_infections)",
        "BỆNH DA VÀ NIÊM MẠC DO CANDIDA (Candidosis)": "chunked_data/BỆNH_DA_VÀ_NIÊM_MẠC_DO_CANDIDA_(Candidosis)",
        "VIÊM DA TIẾP XÚC DỊ ỨNG (Allergic Contact Dermatitis)": "chunked_data/VIÊM_DA_TIẾP_XÚC_DỊ_ỨNG_(Allergic_Contact_Dermatitis)",
        "HỘI CHỨNG DRESS (The Drug Reaction with Eosinophilia and Systemic Symptoms)": "chunked_data/HỘI_CHỨNG_DRESS_(The_Drug_Reaction_with_Eosinophilia_and_Systemic_Symptoms)",
        "BỆNH LẬU (Gonorrhea)": "chunked_data/BỆNH_LẬU_(Gonorrhea)",
        "VIÊM ÂM HỘ-ÂM ĐẠO DO NẤM CANDIDA (Vulvovaginal Candidiasis)": "chunked_data/VIÊM_ÂM_HỘ-ÂM_ĐẠO_DO_NẤM_CANDIDA_(Vulvovaginal_Candidiasis)",
        "SARCOIDOSIS": "chunked_data/SARCOIDOSIS",
        "BỆNH VẢY NẾN (Psoriasis)": "chunked_data/BỆNH_VẢY_NẾN_(Psoriasis)",
        "NHỌT": "chunked_data/NHỌT",
        "HỘI CHỨNG STEVENS-JOHNSON (Stevens-Johnson syndrome - SJS)": "chunked_data/HỘI_CHỨNG_STEVENS-JOHNSON_(Stevens-Johnson_syndrome_-_SJS)",
        "BỆNH GIANG MAI (Syphilis)": "chunked_data/BỆNH_GIANG_MAI_(Syphilis)",
        "BỆNH ZONA": "chunked_data/BỆNH_ZONA",
        "LY THƯỢNG BÌ BỌNG NƯỚC BẨM SINH (Inherited epidermolysis bullosa)": "chunked_data/LY_THƯỢNG_BÌ_BỌNG_NƯỚC_BẨM_SINH_(Inherited_epidermolysis_bullosa)",
        "NẤM TÓC": "chunked_data/NẤM_TÓC",
        "BỆNH LICHEN PHẲNG (Lichen planus)": "chunked_data/BỆNH_LICHEN_PHẲNG_(Lichen_planus)",
        "HỘI CHỨNG BONG VẢY DA DO TỤ CẦU (STAPHYLOCOCCAL SCALDED SKIN SYNDROME - SSSS)": "chunked_data/HỘI_CHỨNG_BONG_VẢY_DA_DO_TỤ_CẦU_(STAPHYLOCOCCAL_SCALDED_SKIN_SYNDROME_-_SSSS)",
        "BỆNH VẢY CÁ MẮC PHẢI": "chunked_data/BỆNH_VẢY_CÁ_MẮC_PHẢI",
        "ĐỎ DA TOÀN THÂN (Erythroderma)": "chunked_data/ĐỎ_DA_TOÀN_THÂN_(Erythroderma)",
        "SẨN NGỨA (Prurigo)": "chunked_data/SẨN_NGỨA_(Prurigo)",
        "DỊ SỪNG NANG LÔNG (Follicular dyskeratosis)": "chunked_data/DỊ_SỪNG_NANG_LÔNG_(Follicular_dyskeratosis)",
        "U ỐNG TUYẾN MỒ HÔI (Syringoma)": "chunked_data/U_ỐNG_TUYẾN_MỒ_HÔI_(Syringoma)",
        "BỆNH GAI ĐEN (Acanthosis nigricans)": "chunked_data/BỆNH_GAI_ĐEN_(Acanthosis_nigricans)",
        "VIÊM NANG LÔNG (Folliculitis)": "chunked_data/VIÊM_NANG_LÔNG_(Folliculitis)",
        "BỌNG NƯỚC DẠNG PEMPHIGUS (Pemphigoid)": "chunked_data/BỌNG_NƯỚC_DẠNG_PEMPHIGUS_(Pemphigoid)",
        "U XƠ THẦN KINH (Neurofibromatosis)": "chunked_data/U_XƠ_THẦN_KINH_(Neurofibromatosis)",
        "BỆNH BẠCH BIẾN (Vitiligo)": "chunked_data/BỆNH_BẠCH_BIẾN_(Vitiligo)",
        "VIÊM DA DẦU (Seborrheic Dermatitis)": "chunked_data/VIÊM_DA_DẦU_(Seborrheic_Dermatitis)",
        "UNG THƯ TẾ BÀO VẢY (Squamous cell carcinoma-SCC)": "chunked_data/UNG_THƯ_TẾ_BÀO_VẢY_(Squamous_cell_carcinoma-SCC)",
        "BỆNH PELLAGRA": "chunked_data/BỆNH_PELLAGRA",
        "HỒNG BAN ĐA DẠNG (Erythema multiforme)": "chunked_data/HỒNG_BAN_ĐA_DẠNG_(Erythema_multiforme)",
        "BỆNH VIÊM DA DẠNG HERPES CỦA DUHRING-BROCQ (Dermatitis Herpetiformis)": "chunked_data/BỆNH_VIÊM_DA_DẠNG_HERPES_CỦA_DUHRING-BROCQ_(Dermatitis_Herpetiformis)",
        "BỆNH HẠT CƠM (Warts)": "chunked_data/BỆNH_HẠT_CƠM_(Warts)",
        "LANG BEN": "chunked_data/LANG_BEN",
        "BỆNH LAO DA": "chunked_data/BỆNH_LAO_DA",
        "BỆNH MÀY ĐAY (Urticaria)": "chunked_data/BỆNH_MÀY_ĐAY_(Urticaria)",
        "BỆNH DA DO ÁNH SÁNG (Photodermatosis)": "chunked_data/BỆNH_DA_DO_ÁNH_SÁNG_(Photodermatosis)",
        "VIÊM DA TIẾP XÚC DO CÔN TRÙNG": "chunked_data/VIÊM_DA_TIẾP_XÚC_DO_CÔN_TRÙNG",
        "DÀY SỪNG LÒNG BÀN TAY, BÀN CHÂN DI TRUYỀN": "chunked_data/DÀY_SỪNG_LÒNG_BÀN_TAY,_BÀN_CHÂN_DI_TRUYỀN",
        "BỆNH PORPHYRIN DA": "chunked_data/BỆNH_PORPHYRIN_DA",
        "VẢY PHẤN HỒNG GIBERT (Pityriasis rosea of Gibert)": "chunked_data/VẢY_PHẤN_HỒNG_GIBERT_(Pityriasis_rosea_of_Gibert)",
        "SẠM DA": "chunked_data/SẠM_DA",
        "Á VẢY NẾN VÀ VẢY PHẤN DẠNG LICHEN (Parapsoriasis and Pityriasis Lichenoides)": "chunked_data/Á_VẢY_NẾN_VÀ_VẢY_PHẤN_DẠNG_LICHEN_(Parapsoriasis_and_Pityriasis_Lichenoides)",
        "VIÊM DA ĐẦU CHI - RUỘT (Acrodermatitis enteropathica)": "chunked_data/VIÊM_DA_ĐẦU_CHI_-_RUỘT_(Acrodermatitis_enteropathica)",
        "BỆNH LUPUS BAN ĐỎ (Lupus Erythematosus)": "chunked_data/BỆNH_LUPUS_BAN_ĐỎ_(Lupus_Erythematosus)",
        "BỆNH PHONG (Leprosy)": "chunked_data/BỆNH_PHONG_(Leprosy)",
        "BỆNH VẢY PHẤN ĐỎ NANG LÔNG (Pityriasis rubra pilaris)": "chunked_data/BỆNH_VẢY_PHẤN_ĐỎ_NANG_LÔNG_(Pityriasis_rubra_pilaris)",
        "BỆNH APTHOSE (Apthosis)": "chunked_data/BỆNH_APTHOSE_(Apthosis)",
        "TRỨNG CÁ (Acne)": "chunked_data/TRỨNG_CÁ_(Acne)",
        "PEMPHIGUS": "chunked_data/PEMPHIGUS"
    }
}