{
  "chunk_id": "UNG THƯ TẾ BÀO VẢY (Squamous cell carcinoma-SCC)_0",
  "disease": "UNG THƯ TẾ BÀO VẢY (Squamous cell carcinoma-SCC)",
  "section": "OVERVIEW",
  "file_name": "UNG_THƯ_TẾ_BÀO_VẢY.txt",
  "content": "1. ĐẠI CƯƠNG\nUng thư tế bào vảy (squamous cell carcinoma-SCC) là ung thư khởi phát từ tế bào sừng của da và niêm mạc, chiếm khoảng 20% các ung thư da và đứng hàng thứ hai sau ung thư tế bào đáy. Ung thư tế bào vảy có thể xâm lấn và di căn xa.\nTrên thế giới, bệnh thường gặp ở những người da trắng với tỷ lệ mới mắc ở Mỹ khoảng hơn 100/100.000 dân, ở Úc là 250/100.000 dân. Bệnh ít gặp hơn ở những người có loại da typ IV, typ V theo phân loại Fitzpatrick (như người châu Á).\nTại Bệnh viện Da liễu Trung ương, số người bị ung thư tế bào vảy đến khám và điều trị ngày càng tăng. Phần lớn người bệnh đến khám muộn, khi tổn thương lan rộng hoặc đã di căn.\n2. CÁC YẾU TỐ NGUY CƠ\nUng thư biểu mô tế bào vảy thường xuất hiện trên các thương tổn da mạn tính như dày sừng ánh sáng (actinic keratosis), bạch sản (leucoplasia), các sẹo bỏng, viêm da do quang tuyến, nhiễm HPV… Sau một thời gian tiến triển kéo dài, trên thương tổn da mạn tính xuất hiện sùi hoặc mảng cứng nổi cao, chắc, màu hồng đến màu đỏ, loét, dễ chảy máu, đóng vảy tiết nâu đen.\n3. CHẨN ĐOÁN"
}