{
  "chunk_id": "BỆNH ZONA_4",
  "disease": "BỆNH ZONA",
  "section": "OVERVIEW",
  "file_name": "ZONA.txt",
  "content": "· Zona cổ (đám rối cổ nông) và cổ cánh tay.\n· Zona gáy cổ: có tổn thương ở gáy, da đầu, vành tai.\n· Zona hông, bụng, sinh dục, bẹn, xương cùng, ụ ngồi, đùi.\n+ Theo hình thái tổn thương: những hình thái này thường gặp ở những người suy giảm miễn dịch như HIV/AIDS, ung thư, hoá trị liệu..., bao gồm:\n· Zona lan toả (disseminated zoster).\n· Zona nhiều dây thần kinh.\n· Zona tái phát.\n+ Các thể zona đặc biệt\n· Zona mắt: chiếm 10-15% các thể zona. Do tổn thương thần kinh V hay thần kinh sinh ba chi phối cho mắt, hàm trên và hàm dưới, trong đó tổn thương nhánh mắt gấp 5 lần các nhánh khác. Có thể có các biến chứng về mắt như viêm kết mạc, giác mạc, củng mạc, thậm chí nặng đe doạ thị lực như hoại tử võng mạc cấp tính, viêm dây thần kinh thị giác, hội chứng đỉnh ổ mắt, viêm hậu củng mạc.\n```text\naucome\nthứ phát...\n· Zona hạch gối hay hội chứng Ramsay Hunt: do thương tổn hạch gối của dây thần kinh VII. Bệnh nhân liệt mặt một bên, ù tai, nghe kém hoặc mất khả năng nghe, buồn nôn, nôn, chóng mặt và giật nhãn cầu. Mắt không nhắm kín được (hở mi), có dấu hiệu Charles Bell. Mất cảm giác vị giác một bên 2/3 trước lưỡi, mụn nước mọc ở màng nhĩ, ống tai, vành tai. Có thể có viêm não, màng não.\n· Zona vùng xương cùng (S2, S3, S4): do viêm dây thần kinh chi phối vùng bàng quang. Bệnh nhân khó tiểu, tiểu dắt, bí tiểu, có trường hợp tiểu máu và tiểu mủ. Đau bụng giống như các triệu chứng ngoại khoa, đau quặn bụng dưới, căng tức, bí trung đại tiện, hậu môn co thắt và cứng như đá không thể khám được, đau nhức vùng da một bên sinh dục kèm theo thương tổn da điển hình.\n· Zona tai: cảm giác rát bỏng, đau vùng tai, có thể lan ra thái dương và gáy. Đau xảy ra từng cơn kéo dài nhiều ngày làm bệnh nhân không ăn, không ngủ được, đặc biệt là zona tai kết hợp với zona họng gây đau họng không nuốt được. Rối loạn cảm giác vùng mặt, liệt mặt ngoại biên, nghe kém."
}