{
  "chunk_id": "HỘI CHỨNG RAYNAUD_10",
  "disease": "HỘI CHỨNG RAYNAUD",
  "section": "OVERVIEW",
  "file_name": "HỘI_CHỨNG_RAYNAUD.txt",
  "content": "d) Thủ thuật cắt bỏ dây thần kinh giao cảm\n- Chỉ định cho những trường hợp bệnh nặng, cấp tính hoặc dai dẳng, không đáp ứng với các phương pháp điều trị khác.\n- Thủ thuật cắt thần kinh giao cảm thắt lưng rất có hiệu quả trong những trường hợp hội chứng Raynaud nặng ở chân.\n- Thủ thuật cắt thần kinh giao cảm chọn lọc ở các ngón tay dùng để giảm đau và điều trị các vết loét ở đầu ngón do thiếu máu nuôi dưỡng.\n- Tuy nhiên, biện pháp này không có hiệu quả lâu dài."
}