{
  "chunk_id": "VẢY PHẤN HỒNG GIBERT (Pityriasis rosea of Gibert)_1",
  "disease": "VẢY PHẤN HỒNG GIBERT (Pityriasis rosea of Gibert)",
  "section": "OVERVIEW",
  "file_name": "VẢY_PHẤN_HỒNG_GIBERT.txt",
  "content": "a) Chẩn đoán xác định: chủ yếu dựa vào các đặc điểm lâm sàng.\n- Lâm sàng\n+ Thương tổn tiên phát (dát Herald)\nDát hình tròn hay bầu dục, hình huy hiệu\nGiới hạn rõ ràng\nKích thước 2-10 cm\nBờ xung quanh màu hồng tươi, vùng giữa nhạt màu và hơi nhăn nheo, có vảy da ở giữa hai vùng, vảy dính vào da ở phía ngoài và bờ tự do ở phía trong.\nThương tổn có xu hướng lan ra xung quanh.\nVị trí: thân mình, cổ hoặc gốc chi.\n+ Thương tổn thứ phát\nXuất hiện 2-20 ngày sau thương tổn tiên phát.\nCác dát đỏ hình huy hiệu, kích thước nhỏ hơn.\nCác sẩn màu hồng, hơi nổi cao trên mặt da.\nThương tổn sắp xếp theo nếp căng da và tạo nên hình ảnh giống cây thông.\n+ Cơ năng: 25% bệnh nhân ngứa.\n+ Toàn trạng:\nThường không bị ảnh hưởng.\nMột số trường hợp có thể chóng mặt, buồn nôn, ăn kém, sốt nhẹ, đau cơ hoặc đau đầu.\n- Cận lâm sàng:\n+ Mô bệnh học không đặc hiệu, có thâm nhiễm tế bào viêm ở nhú bì.\n+ Hóa mô miễn dịch chủ yếu tế bào TCD4 dương tính.\n+ Xét nghiệm nấm âm tính.\n+ Xét nghiệm sinh hóa bình thường."
}